quickwindow/__init__.py
quickwindow/event.py
quickwindow/glfw.py
quickwindow/quick.py
quickwindow/window.py
quickwindow-0.1.0.dist-info/licenses/LICENSE
quickwindow-0.1.0.dist-info/METADATA
quickwindow-0.1.0.dist-info/WHEEL
quickwindow-0.1.0.dist-info/top_level.txt
quickwindow-0.1.0.dist-info/RECORD
