Metadata-Version: 2.4
Name: quickwindow
Version: 0.1.0
Summary: Python bindings for the GLFW library (pyglfw fork)
Home-page: https://github.com/takeiteasy/quickwindow
Author: George Watson
Author-email: George Watson <gigolo@hotmail.co.uk>
Project-URL: Homepage, https://github.com/takeiteasy/quickwindow
Project-URL: Issues, https://github.com/takeiteasy/quickwindow/issues
Classifier: Programming Language :: Python :: 3
Classifier: License :: OSI Approved :: MIT License
Classifier: Operating System :: OS Independent
Requires-Python: >=3.10
License-File: LICENSE
Dynamic: author
Dynamic: home-page
Dynamic: license-file
